{
	"format_version": "1.8.0",
	"animations": {
		"animation.dlw.walk": {
			"loop": true,
			"animation_length": 0.83333,
			"bones": {
				"lFoot": {
					"position": {
						"0.0": {
							"vector": [0, 4, -11]
						},
						"0.4167": {
							"vector": [0, 0, 0]
						},
						"0.8333": {
							"vector": [0, 4, -11]
						}
					}
				},
				"rFoot": {
					"rotation": {
						"0.0": {
							"vector": [0, 0, 0]
						},
						"0.4167": {
							"vector": [-5, 0, 0]
						},
						"0.8333": {
							"vector": [0, 0, 0]
						}
					},
					"position": {
						"0.0": {
							"vector": [0, 0, 0]
						},
						"0.4167": {
							"vector": [0, 6, -13]
						},
						"0.8333": {
							"vector": [0, 0, 0]
						}
					}
				},
				"lLeg": {
					"rotation": {
						"0.0": {
							"vector": [-35, 0, 0]
						},
						"0.4167": {
							"vector": [0, 0, 0]
						},
						"0.8333": {
							"vector": [-35, 0, 0]
						}
					},
					"position": {
						"0.0": {
							"vector": [0, 7, -21]
						},
						"0.4167": {
							"vector": [0, 0, 0]
						},
						"0.8333": {
							"vector": [0, 7, -21]
						}
					}
				},
				"lLegDown": {
					"rotation": {
						"0.0": {
							"vector": [37.5, 0, 0]
						},
						"0.4167": {
							"vector": [0, 0, 0]
						},
						"0.8333": {
							"vector": [37.5, 0, 0]
						}
					},
					"position": {
						"0.0": {
							"vector": [0, 3, 10]
						},
						"0.4167": {
							"vector": [0, 0, 0]
						},
						"0.8333": {
							"vector": [0, 3, 10]
						}
					}
				},
				"rLeg": {
					"rotation": {
						"0.0": {
							"vector": [0, 0, 0]
						},
						"0.4167": {
							"vector": [-37.5, 0, 0]
						},
						"0.8333": {
							"vector": [0, 0, 0]
						}
					},
					"position": {
						"0.0": {
							"vector": [0, 0, 0]
						},
						"0.4167": {
							"vector": [0, 8, -21]
						},
						"0.8333": {
							"vector": [0, 0, 0]
						}
					}
				},
				"rLegDown": {
					"rotation": {
						"0.0": {
							"vector": [0, 0, 0]
						},
						"0.4167": {
							"vector": [30, 0, 0]
						},
						"0.8333": {
							"vector": [0, 0, 0]
						}
					},
					"position": {
						"0.0": {
							"vector": [0, 0, 0]
						},
						"0.4167": {
							"vector": [0, 3, 8]
						},
						"0.8333": {
							"vector": [0, 0, 0]
						}
					}
				},
				"lArm": {
					"rotation": {
						"0.0": {
							"vector": [-25, 0, 0]
						},
						"0.4167": {
							"vector": [0, 0, 0]
						},
						"0.8333": {
							"vector": [-22.5, 0, 0]
						}
					},
					"position": {
						"0.0": {
							"vector": [0, 6, -24]
						},
						"0.4167": {
							"vector": [0, 0, 0]
						},
						"0.8333": {
							"vector": [0, 6, -22]
						}
					}
				},
				"rArm": {
					"rotation": {
						"0.0": {
							"vector": [0, 0, 0]
						},
						"0.4167": {
							"vector": [-35, 0, 0]
						},
						"0.8333": {
							"vector": [0, 0, 0]
						}
					},
					"position": {
						"0.0": {
							"vector": [0, 0, 0]
						},
						"0.4167": {
							"vector": [0, 12, -33]
						},
						"0.8333": {
							"vector": [0, 0, 0]
						}
					}
				},
				"rArmDown": {
					"position": {
						"vector": [0, 0, 0]
					}
				}
			}
		},
		"animation.dlw.idle": {
			"loop": "hold_on_last_frame",
			"animation_length": 5,
			"bones": {
				"lFoot": {
					"rotation": {
						"0.0": {
							"vector": [0, 0, 0]
						},
						"0.3333": {
							"vector": [16.73634, 5.188, -16.73634]
						}
					},
					"position": {
						"0.0": {
							"vector": [0, 0, 0]
						},
						"0.3333": {
							"vector": [6, 3, 7]
						}
					}
				},
				"rFoot": {
					"rotation": {
						"0.0": {
							"vector": [0, 0, 0]
						},
						"0.3333": {
							"vector": [0, 0, 12.5]
						}
					},
					"position": {
						"0.0": {
							"vector": [0, 0, 0]
						},
						"0.3333": {
							"vector": [-4, 1, -4]
						}
					}
				},
				"lLeg": {
					"rotation": {
						"0.0": {
							"vector": [0, 0, 0]
						},
						"0.3333": {
							"vector": [14.524, -3.71052, -9.1308]
						}
					},
					"position": {
						"0.0": {
							"vector": [0, 0, 0]
						},
						"0.3333": {
							"vector": [6, 3, 8]
						}
					}
				},
				"lLegDown": {
					"rotation": {
						"vector": [0, 0, 0]
					}
				},
				"lLegUp": {
					"rotation": {
						"vector": [0, 0, 0]
					},
					"position": {
						"vector": [0, 0, 0]
					}
				},
				"rLeg": {
					"rotation": {
						"0.0": {
							"vector": [0, 0, 0]
						},
						"0.3333": {
							"vector": [-10, 0, 0]
						}
					},
					"position": {
						"0.0": {
							"vector": [0, 0, 0]
						},
						"0.3333": {
							"vector": [0, 1, -6]
						}
					}
				},
				"rLegDown": {
					"rotation": {
						"0.0": {
							"vector": [0, 0, 0]
						},
						"0.3333": {
							"vector": [1.46257, -1.66165, 16.0936]
						}
					},
					"position": {
						"0.0": {
							"vector": [0, 0, 0]
						},
						"0.3333": {
							"vector": [-5, 0, 1]
						}
					}
				},
				"rLegUp": {
					"rotation": {
						"vector": [0, 0, 0]
					},
					"position": {
						"vector": [0, 0, 0]
					}
				},
				"lArm": {
					"rotation": {
						"0.0": {
							"vector": [0, 0, 0]
						},
						"0.3333": {
							"vector": [0, 0, -27.5]
						}
					},
					"position": {
						"0.0": {
							"vector": [0, 0, 0]
						},
						"0.3333": {
							"vector": [26, 0, 0]
						}
					}
				},
				"rArm": {
					"rotation": {
						"0.0": {
							"vector": [0, 0, 0]
						},
						"0.3333": {
							"vector": [0, 0, 35]
						}
					},
					"position": {
						"0.0": {
							"vector": [0, 0, 0]
						},
						"0.3333": {
							"vector": [-28, 18, 0]
						}
					}
				},
				"rArmDown": {
					"rotation": {
						"0.0": {
							"vector": [0, 0, 0]
						},
						"0.3333": {
							"vector": [0, 0, -65]
						}
					},
					"position": {
						"0.0": {
							"vector": [0, 0, 0]
						},
						"0.3333": {
							"vector": [47, 13, 0]
						}
					}
				},
				"lArmUp": {
					"rotation": {
						"vector": [0, 0, 0]
					},
					"position": {
						"vector": [0, 0, 0]
					}
				},
				"lArmDown": {
					"rotation": {
						"0.0": {
							"vector": [0, 0, 0]
						},
						"0.3333": {
							"vector": [0, 0, 50]
						}
					},
					"position": {
						"0.0": {
							"vector": [0, 0, 0]
						},
						"0.3333": {
							"vector": [-30, 27, 0]
						}
					}
				}
			}
		},
		"animation.dlw.attack": {
			"loop": true
		}
	},
	"geckolib_format_version": 2
}